plugins/README.md
plugins/openacc_detector.py
plugins/openfoam_detector.py
plugins/openfoam_reflections_detector.py
plugins/openmp_detector.py
foamcd/__init__.py
foamcd/common.py
foamcd/config.py
foamcd/db.py
foamcd/entity.py
foamcd/feature_detectors.py
foamcd/git.py
foamcd/logs.py
foamcd/markdown.py
foamcd/markdown_base.py
foamcd/markdown_class_index.py
foamcd/markdown_concepts_index.py
foamcd/markdown_functions_index.py
foamcd/parse.py
foamcd/plugin_system.py
foamcd/tree_sitter_subparser.py
foamcd/unittesting.py
foamcd/version.py
foamcd-0.1.2.dist-info/METADATA
foamcd-0.1.2.dist-info/WHEEL
foamcd-0.1.2.dist-info/entry_points.txt
foamcd-0.1.2.dist-info/RECORD
