Metadata-Version: 2.4
Name: foamCD
Version: 0.1.2
Summary: Highlighy opinionated ways to document OpenFOAM-like c++ libraries
Project-URL: Homepage, https://github.com/FoamScience/foamCD
Project-URL: Bug Tracker, https://github.com/FoamScience/foamCD/issues
Classifier: Development Status :: 4 - Beta
Classifier: License :: OSI Approved :: MIT License
Classifier: Operating System :: OS Independent
Classifier: Programming Language :: Python :: 3
Requires-Python: >=3.12
Requires-Dist: clang>=20.1.0
Requires-Dist: colorlog>=6.9.0
Requires-Dist: cppyy>=3.5.0
Requires-Dist: cpycppyy>=1.13.0
Requires-Dist: jinja2>=3.1.6
Requires-Dist: libclang>=18.1.1
Requires-Dist: omegaconf>=2.3.0
Requires-Dist: python-frontmatter>=1.1.0
Requires-Dist: tomli>=2.2.1
Requires-Dist: tree-sitter-cpp>=0.23.4
Requires-Dist: tree-sitter>=0.24.0
